singlem/__init__.py
singlem/__main__.py
singlem/appraisal_result.py
singlem/appraiser.py
singlem/archive_otu_table.py
singlem/chainsaw.py
singlem/checkm2.py
singlem/clusterer.py
singlem/condense.py
singlem/diamond_parser.py
singlem/diamond_spkg_searcher.py
singlem/genome_fasta_mux.py
singlem/genome_size.py
singlem/graftm_result.py
singlem/hmm_logo.py
singlem/kingfisher_sra.py
singlem/known_otu_table.py
singlem/lyrebird.py
singlem/main.py
singlem/metagenome_otu_finder.py
singlem/metapackage.py
singlem/metapackage_read_name_store.py
singlem/ordered_set.py
singlem/orf_length_checker.py
singlem/otu_table.py
singlem/otu_table_collection.py
singlem/otu_table_entry.py
singlem/package_creator.py
singlem/pipe.py
singlem/pipe_sequence_extractor.py
singlem/pipe_taxonomy_assigner_by_query.py
singlem/placement_parser.py
singlem/querier.py
singlem/query_formatters.py
singlem/rarefier.py
singlem/read_fraction.py
singlem/regenerator.py
singlem/renew.py
singlem/run_via_os_system.py
singlem/sequence_classes.py
singlem/sequence_database.py
singlem/sequence_extractor.py
singlem/singlem_database_models.py
singlem/singlem_package.py
singlem/strain_summariser.py
singlem/streaming_hmm_search_result.py
singlem/summariser.py
singlem/supplement.py
singlem/taxonomy.py
singlem/taxonomy_bihash.py
singlem/trim_package_hmms.py
singlem/utils.py
singlem/version.py
singlem/biolib_lite/__init__.py
singlem/biolib_lite/common.py
singlem/biolib_lite/custom_help_formatter.py
singlem/biolib_lite/exceptions.py
singlem/biolib_lite/execute.py
singlem/biolib_lite/logger.py
singlem/biolib_lite/newick.py
singlem/biolib_lite/parallel.py
singlem/biolib_lite/prodigal_biolib.py
singlem/biolib_lite/seq_io.py
singlem/biolib_lite/taxonomy.py
singlem-0.20.3.dist-info/licenses/LICENCE.txt
singlem-0.20.3.dist-info/METADATA
singlem-0.20.3.dist-info/WHEEL
singlem-0.20.3.dist-info/entry_points.txt
singlem-0.20.3.dist-info/top_level.txt
singlem-0.20.3.dist-info/RECORD
