Metadata-Version: 2.4
Name: singlem
Version: 0.20.3
Summary: Novelty-inclusive microbial community profiling of shotgun metagenomes
Author: Ben Woodcroft
License-Expression: GPL-3.0-or-later
Project-URL: Homepage, https://github.com/wwood/SingleM
Keywords: metagenomics,bioinformatics
Classifier: Development Status :: 4 - Beta
Classifier: Topic :: Scientific/Engineering
Classifier: Topic :: Scientific/Engineering :: Bio-Informatics
Classifier: Programming Language :: Python :: 3
Requires-Python: >=3.7
License-File: LICENCE.txt
Requires-Dist: biopython==1.86
Requires-Dist: extern==0.4.1
Requires-Dist: fastalite
Requires-Dist: graftm==0.15.1
Requires-Dist: Jinja2==3.1.6
Requires-Dist: pandas==2.3.3
Requires-Dist: pip==25.2
Requires-Dist: polars==1.35.1
Requires-Dist: pyarrow==22.0.0
Requires-Dist: pyranges==0.1.4
Requires-Dist: seqmagick==0.8.6
Requires-Dist: SQLAlchemy==2.0.44
Requires-Dist: sqlparse==0.5.3
Requires-Dist: squarify==0.4.3
Requires-Dist: tqdm==4.67.1
Requires-Dist: zenodo_backpack==0.4.0
Dynamic: license-file
